{
  "": "https://gitlab.com/kicad/code/kicad/-/raw/master/kicad/pcm/schemas/pcm.v1.schema.json#/definitions/Repository",
  "maintainer": {
    "contact": { "web": "https://github.com/VinciEcoDrive/VED-KiCad-Libraries" },
    "name": "VinciEcoDrive"
  },
  "name": "VinciEcoDrive repository",
  "packages": {
    "sha256": "33e9cdb18e59135dbf0c3971901d5a739bd318d61c588045fdfc1ea790dd1fc5",
    "update_time_utc": "2025-11-07 10:45:34",
    "update_timestamp": 1762512334,
    "url": "https://vinciecodrive.github.io/VED-KiCad-Libraries/packages.json"
  }
}
