{
  "": "https://gitlab.com/kicad/code/kicad/-/raw/master/kicad/pcm/schemas/pcm.v1.schema.json#/definitions/Repository",
  "maintainer": {
    "contact": { "web": "https://github.com/VinciEcoDrive/VED-KiCad-Libraries" },
    "name": "VinciEcoDrive"
  },
  "name": "VinciEcoDrive repository",
  "packages": {
    "sha256": "53460f1b7af8fadf74975a229f51500ec3298cc85e0c7fe20f3609c873d5b9d6",
    "update_time_utc": "2025-11-06 11:50:30",
    "update_timestamp": 1762429830,
    "url": "https://vinciecodrive.github.io/VED-KiCad-Libraries/packages.json"
  }
}
